Metadata-Version: 2.1
Name: Dbase-connectors
Version: 0.1.0
Author: Lakhdar Belkharroubi
License-File: license.txt
